{"response":{"latest":[{"name":"Bonus hunt #990","slug":"990","bonushunt_status":"Opening","bonushunt_bonus":66,"bonushunt_balance":5200000,"date":1697185028594,"bonushunt_currency":"$"},{"name":"Bonus hunt #989","slug":"989","bonushunt_status":"Ended","bonushunt_bonus":66,"bonushunt_balance":6000000,"date":1697108405483,"bonushunt_currency":"$"},{"name":"Bonus hunt #988","slug":"988","bonushunt_status":"Ended","bonushunt_bonus":70,"bonushunt_balance":9000000,"date":1697019700605,"bonushunt_currency":"$"},{"name":"Bonus hunt #987","slug":"987","bonushunt_status":"Ended","bonushunt_bonus":78,"bonushunt_balance":2000000,"date":1696934525819,"bonushunt_currency":"$"},{"name":"Bonus hunt #986","slug":"986","bonushunt_status":"Ended","bonushunt_bonus":37,"bonushunt_balance":2500000,"date":1696927827158,"bonushunt_currency":"$"},{"name":"Bonus hunt #985","slug":"985","bonushunt_status":"Ended","bonushunt_bonus":69,"bonushunt_balance":8500000,"date":1696755734027,"bonushunt_currency":"$"}],"stats":{"bonushunt_casinos":[{"casino_name":"Vegaz","casino_slug":"vgz"}],"bonushunt_slug":"372","bonushunt_general":{"bonushunt_name":"Bonus hunt #372","bonushunt_slug":"372","bonushunt_status":"Ended","bonushunt_total_bonuses":24,"bonushunt_total_win":238428,"bonushunt_current_bonus":24,"bonushunt_date":1621144677442,"bonushunt_total_cost":92000,"bonushunt_cost_bonus":3833,"bonushunt_win_bonus":9935,"bonushunt_avg":84,"bonushunt_avg_win":9935,"bonushunt_avg_mp":122.89,"bonushunt_break_even_mp":0,"bonushunt_currency":"\u20ac"},"bonushunt_balance":{"start_balance":788000,"current_balance":933386,"profit":145386},"bonushunt_wager":{"start_wager":360000,"current_wager":360000,"profit":0},"bonushunt_highest_multiplier":{"slot_name":"The Dog House Megaways","slot_mp":1130},"bonushunt_highest_win":{"slot_name":"The Dog House Megaways","slot_win":56500},"bonushunt_providers":[{"provider_name":"Gameart","provider_alias":"GA","provider_win":56040},{"provider_name":"Nolimit City","provider_alias":"NoLC","provider_win":17553},{"provider_name":"Pragmatic Play","provider_alias":"Prag","provider_win":11640},{"provider_name":"NetEnt","provider_alias":"NEnt","provider_win":11180},{"provider_name":"Yggdrasil","provider_alias":"Yggd","provider_win":8985},{"provider_name":"Thunderkick","provider_alias":"Thun","provider_win":3364.1666666666665},{"provider_name":"Hacksaw Gaming","provider_alias":"Hack","provider_win":1250},{"provider_name":"Push Gaming","provider_alias":"Push","provider_win":307.3333333333333}],"bonushunt_time":{"hunt_start":1621144677442,"opening_start":1621153519622,"bonushunt_end":1621158748780,"hunt_duration":8842242,"opening_duration":5229158,"bonushunt_duration":14071400}},"related":{"bonushunt_offers":[{"offer_tier_color_top":"04041B","offer_tier_color_bottom":"04041B","offer_deposit_code":null,"offer_registration_code":"ROSH","offer_casino_tier":"Default","offer_image":"https:\/\/cdn.roshtest.com\/images\/casino\/2022\/03\/1646916265.svg","offer_image_title":"Stake Logo","offer_image_alt":"Stake Logo","offer_text":{"line_first":"NEW EXCLUSIVE OFFER","line_second":"200% up to $3.000","line_third":"USE CODE: \"ROSH\"","line_fourth":"ON SIGNUP"},"offer_flags":[{"offer_flag_name":"Non-Sticky","offer_flag_description":"Non-sticky bonus allows the separation of deposit and bonus amounts, giving the ability to play with deposit money first and to withdraw any winnings before playing with the bonus money.","offer_flag_color":"F8488E"},{"offer_flag_name":"Exclusive","offer_flag_description":"Special and generous bonus offers.","offer_flag_color":"FF9A33"},{"offer_flag_name":"Store","offer_flag_description":"This casino has store items available.","offer_flag_color":"B0BEE8"},{"offer_flag_name":"Crypto","offer_flag_description":"","offer_flag_color":"FF5263"}],"offer_redirect":"stake-7"},{"offer_tier_color_top":"04041B","offer_tier_color_bottom":"04041B","offer_deposit_code":"100FIRST","offer_registration_code":"ROSH10","offer_casino_tier":"Default","offer_image":"https:\/\/cdn.roshtest.com\/images\/casino\/2022\/12\/1669979972.e9c97903","offer_image_title":"logo1","offer_image_alt":"logo1","offer_text":{"line_first":"Welcome bonus","line_second":"10 signup spins","line_third":"100% up to \u20ac400","line_fourth":"100 free spins"},"offer_flags":[{"offer_flag_name":"Exclusive","offer_flag_description":"Special and generous bonus offers.","offer_flag_color":"FF9A33"},{"offer_flag_name":"Crypto","offer_flag_description":"","offer_flag_color":"FF5263"},{"offer_flag_name":"Cashback","offer_flag_description":"This casino gives part of player\u2019s money back.","offer_flag_color":"19FFA6"}],"offer_redirect":"depositwin-105"},{"offer_tier_color_top":"04041B","offer_tier_color_bottom":"04041B","offer_deposit_code":null,"offer_registration_code":null,"offer_casino_tier":"Default","offer_image":"https:\/\/cdn.roshtest.com\/images\/casino\/2022\/06\/1655299183.svg","offer_image_title":"logo1","offer_image_alt":"logo1","offer_text":{"line_first":"Welcome bonus","line_second":"200% up to \u20ac2.000","line_third":"50 free spins","line_fourth":null},"offer_flags":[{"offer_flag_name":"Exclusive","offer_flag_description":"Special and generous bonus offers.","offer_flag_color":"FF9A33"},{"offer_flag_name":"Non-Sticky","offer_flag_description":"Non-sticky bonus allows the separation of deposit and bonus amounts, giving the ability to play with deposit money first and to withdraw any winnings before playing with the bonus money.","offer_flag_color":"F8488E"}],"offer_redirect":"ice-casino-86"},{"offer_tier_color_top":"04041B","offer_tier_color_bottom":"04041B","offer_deposit_code":"WELCOME200","offer_registration_code":null,"offer_casino_tier":"Default","offer_image":"https:\/\/cdn.roshtest.com\/images\/casino\/2023\/02\/1676029136.png","offer_image_title":"pribet","offer_image_alt":"pribet","offer_text":{"line_first":"Welcome bonus","line_second":"100% up to \u20ac200","line_third":null,"line_fourth":null},"offer_flags":[{"offer_flag_name":"Crypto","offer_flag_description":"","offer_flag_color":"FF5263"}],"offer_redirect":"pribet-112"}]},"gtb":{"bonushunt_gtb_reward":null,"bonushunt_gtb_countdown":0,"bonushunt_gtb_timer":0,"bonushunt_gtb_stake_required":1,"bonushunt_gtb_guess":null,"bonushunt_gtb_reguessed":null,"bonushunt_gtb_result":238428,"bonushunt_gtb_total":0,"bonushunt_gtb_total_bonuses":24,"bonushunt_gtb_current_bonus":24,"bonushunt_gtb_ended":true},"slots":{"slots":[{"bonushunt_slot_position":1,"bonushunt_slot_name":"Jammin' Jars","bonushunt_slot_provider":"Push Gaming","bonushunt_slot_bet":40,"bonushunt_slot_win":562,"bonushunt_slot_currency":"\u20ac","bonushunt_slot_mp":14.05,"bonushunt_slot_opened":0,"bonushunt_slot_next":0,"bonushunt_casino_name":"Vegaz"},{"bonushunt_slot_position":2,"bonushunt_slot_name":"Buffalo King","bonushunt_slot_provider":"Pragmatic Play","bonushunt_slot_bet":48,"bonushunt_slot_win":720,"bonushunt_slot_currency":"\u20ac","bonushunt_slot_mp":15,"bonushunt_slot_opened":0,"bonushunt_slot_next":0,"bonushunt_casino_name":"Vegaz"},{"bonushunt_slot_position":3,"bonushunt_slot_name":"Big Bass Bonanza","bonushunt_slot_provider":"Pragmatic Play","bonushunt_slot_bet":50,"bonushunt_slot_win":3400,"bonushunt_slot_currency":"\u20ac","bonushunt_slot_mp":68,"bonushunt_slot_opened":0,"bonushunt_slot_next":0,"bonushunt_casino_name":"Vegaz"},{"bonushunt_slot_position":4,"bonushunt_slot_name":"Razor Shark","bonushunt_slot_provider":"Push Gaming","bonushunt_slot_bet":50,"bonushunt_slot_win":320,"bonushunt_slot_currency":"\u20ac","bonushunt_slot_mp":6.4,"bonushunt_slot_opened":0,"bonushunt_slot_next":0,"bonushunt_casino_name":"Vegaz"},{"bonushunt_slot_position":5,"bonushunt_slot_name":"The Dog House","bonushunt_slot_provider":"Pragmatic Play","bonushunt_slot_bet":50,"bonushunt_slot_win":1877,"bonushunt_slot_currency":"\u20ac","bonushunt_slot_mp":37.54,"bonushunt_slot_opened":0,"bonushunt_slot_next":0,"bonushunt_casino_name":"Vegaz"},{"bonushunt_slot_position":6,"bonushunt_slot_name":"Beat The Beast: Griffin's Gold","bonushunt_slot_provider":"Thunderkick","bonushunt_slot_bet":50,"bonushunt_slot_win":1125,"bonushunt_slot_currency":"\u20ac","bonushunt_slot_mp":22.5,"bonushunt_slot_opened":0,"bonushunt_slot_next":0,"bonushunt_casino_name":"Vegaz"},{"bonushunt_slot_position":7,"bonushunt_slot_name":"Beat The Beast: Cerberus' Inferno","bonushunt_slot_provider":"Thunderkick","bonushunt_slot_bet":50,"bonushunt_slot_win":3225,"bonushunt_slot_currency":"\u20ac","bonushunt_slot_mp":64.5,"bonushunt_slot_opened":0,"bonushunt_slot_next":0,"bonushunt_casino_name":"Vegaz"},{"bonushunt_slot_position":8,"bonushunt_slot_name":"Beat The Beast: Quetzalcoatl's Trial","bonushunt_slot_provider":"Thunderkick","bonushunt_slot_bet":50,"bonushunt_slot_win":4625,"bonushunt_slot_currency":"\u20ac","bonushunt_slot_mp":92.5,"bonushunt_slot_opened":0,"bonushunt_slot_next":0,"bonushunt_casino_name":"Vegaz"},{"bonushunt_slot_position":9,"bonushunt_slot_name":"Beat The Beast: Kraken's Lair","bonushunt_slot_provider":"Thunderkick","bonushunt_slot_bet":50,"bonushunt_slot_win":2825,"bonushunt_slot_currency":"\u20ac","bonushunt_slot_mp":56.5,"bonushunt_slot_opened":0,"bonushunt_slot_next":0,"bonushunt_casino_name":"Vegaz"},{"bonushunt_slot_position":10,"bonushunt_slot_name":"The Dog House Megaways","bonushunt_slot_provider":"Pragmatic Play","bonushunt_slot_bet":50,"bonushunt_slot_win":56500,"bonushunt_slot_currency":"\u20ac","bonushunt_slot_mp":1130,"bonushunt_slot_opened":0,"bonushunt_slot_next":0,"bonushunt_casino_name":"Vegaz"},{"bonushunt_slot_position":11,"bonushunt_slot_name":"Beat The Beast: Mighty Sphinx","bonushunt_slot_provider":"Thunderkick","bonushunt_slot_bet":50,"bonushunt_slot_win":5125,"bonushunt_slot_currency":"\u20ac","bonushunt_slot_mp":102.5,"bonushunt_slot_opened":0,"bonushunt_slot_next":0,"bonushunt_casino_name":"Vegaz"},{"bonushunt_slot_position":12,"bonushunt_slot_name":"Big Fin Bay","bonushunt_slot_provider":"Thunderkick","bonushunt_slot_bet":50,"bonushunt_slot_win":3260,"bonushunt_slot_currency":"\u20ac","bonushunt_slot_mp":65.2,"bonushunt_slot_opened":0,"bonushunt_slot_next":0,"bonushunt_casino_name":"Vegaz"},{"bonushunt_slot_position":13,"bonushunt_slot_name":"Da Vinci's Treasure","bonushunt_slot_provider":"Pragmatic Play","bonushunt_slot_bet":50,"bonushunt_slot_win":1570,"bonushunt_slot_currency":"\u20ac","bonushunt_slot_mp":31.4,"bonushunt_slot_opened":0,"bonushunt_slot_next":0,"bonushunt_casino_name":"Vegaz"},{"bonushunt_slot_position":14,"bonushunt_slot_name":"El Paso","bonushunt_slot_provider":"Nolimit City","bonushunt_slot_bet":50,"bonushunt_slot_win":3196,"bonushunt_slot_currency":"\u20ac","bonushunt_slot_mp":63.92,"bonushunt_slot_opened":0,"bonushunt_slot_next":0,"bonushunt_casino_name":"Vegaz"},{"bonushunt_slot_position":15,"bonushunt_slot_name":"Chaos Crew","bonushunt_slot_provider":"Hacksaw Gaming","bonushunt_slot_bet":50,"bonushunt_slot_win":1250,"bonushunt_slot_currency":"\u20ac","bonushunt_slot_mp":25,"bonushunt_slot_opened":0,"bonushunt_slot_next":0,"bonushunt_casino_name":"Vegaz"},{"bonushunt_slot_position":16,"bonushunt_slot_name":"Multifly","bonushunt_slot_provider":"Yggdrasil","bonushunt_slot_bet":75,"bonushunt_slot_win":8985,"bonushunt_slot_currency":"\u20ac","bonushunt_slot_mp":119.8,"bonushunt_slot_opened":0,"bonushunt_slot_next":0,"bonushunt_casino_name":"Vegaz"},{"bonushunt_slot_position":17,"bonushunt_slot_name":"Book Of Shadows","bonushunt_slot_provider":"Nolimit City","bonushunt_slot_bet":100,"bonushunt_slot_win":31910,"bonushunt_slot_currency":"\u20ac","bonushunt_slot_mp":319.1,"bonushunt_slot_opened":0,"bonushunt_slot_next":0,"bonushunt_casino_name":"Vegaz"},{"bonushunt_slot_position":18,"bonushunt_slot_name":"Mystery Museum","bonushunt_slot_provider":"Push Gaming","bonushunt_slot_bet":100,"bonushunt_slot_win":40,"bonushunt_slot_currency":"\u20ac","bonushunt_slot_mp":0.4,"bonushunt_slot_opened":0,"bonushunt_slot_next":0,"bonushunt_casino_name":"Vegaz"},{"bonushunt_slot_position":19,"bonushunt_slot_name":"Floating Dragon","bonushunt_slot_provider":"Pragmatic Play","bonushunt_slot_bet":100,"bonushunt_slot_win":9050,"bonushunt_slot_currency":"\u20ac","bonushunt_slot_mp":90.5,"bonushunt_slot_opened":0,"bonushunt_slot_next":0,"bonushunt_casino_name":"Vegaz"},{"bonushunt_slot_position":20,"bonushunt_slot_name":"Buffalo King Megaways","bonushunt_slot_provider":"Pragmatic Play","bonushunt_slot_bet":100,"bonushunt_slot_win":22760,"bonushunt_slot_currency":"\u20ac","bonushunt_slot_mp":227.6,"bonushunt_slot_opened":0,"bonushunt_slot_next":0,"bonushunt_casino_name":"Vegaz"},{"bonushunt_slot_position":21,"bonushunt_slot_name":"Gates Of Olympus","bonushunt_slot_provider":"Pragmatic Play","bonushunt_slot_bet":100,"bonushunt_slot_win":8328,"bonushunt_slot_currency":"\u20ac","bonushunt_slot_mp":83.28,"bonushunt_slot_opened":0,"bonushunt_slot_next":0,"bonushunt_casino_name":"Vegaz"},{"bonushunt_slot_position":22,"bonushunt_slot_name":"Phoenix Forge","bonushunt_slot_provider":"Pragmatic Play","bonushunt_slot_bet":100,"bonushunt_slot_win":555,"bonushunt_slot_currency":"\u20ac","bonushunt_slot_mp":5.55,"bonushunt_slot_opened":0,"bonushunt_slot_next":0,"bonushunt_casino_name":"Vegaz"},{"bonushunt_slot_position":23,"bonushunt_slot_name":"Rosh - Immortality Cube","bonushunt_slot_provider":"Gameart","bonushunt_slot_bet":200,"bonushunt_slot_win":56040,"bonushunt_slot_currency":"\u20ac","bonushunt_slot_mp":280.2,"bonushunt_slot_opened":0,"bonushunt_slot_next":0,"bonushunt_casino_name":"Vegaz"},{"bonushunt_slot_position":24,"bonushunt_slot_name":"Lost Relics","bonushunt_slot_provider":"NetEnt","bonushunt_slot_bet":400,"bonushunt_slot_win":11180,"bonushunt_slot_currency":"\u20ac","bonushunt_slot_mp":27.95,"bonushunt_slot_opened":0,"bonushunt_slot_next":0,"bonushunt_casino_name":"Vegaz"}],"next_slot":null,"total_casinos":1}},"status":200}